deale_shared_library/Cognito.py
deale_shared_library/DynamoDB.py
deale_shared_library/DynamoDB_test.py
deale_shared_library/Lambda.py
deale_shared_library/__init__.py
deale_shared_library-0.0.7.dist-info/METADATA
deale_shared_library-0.0.7.dist-info/WHEEL
deale_shared_library-0.0.7.dist-info/top_level.txt
deale_shared_library-0.0.7.dist-info/RECORD
