Metadata-Version: 2.1
Name: deale-shared-library
Version: 0.0.7
Summary: A shared library for Deale microservices
Classifier: Development Status :: 3 - Alpha
Classifier: Intended Audience :: Developers
Classifier: License :: OSI Approved :: MIT License
Classifier: Programming Language :: Python :: 3.8
Requires-Dist: boto3
